LaTeXCalculator/__init__.py
LaTeXCalculator/calculator.py
LaTeXCalculator/interactive_calculator.py
latexcalculator-1.0.1.dist-info/METADATA
latexcalculator-1.0.1.dist-info/WHEEL
latexcalculator-1.0.1.dist-info/entry_points.txt
latexcalculator-1.0.1.dist-info/top_level.txt
latexcalculator-1.0.1.dist-info/RECORD
