Metadata-Version: 2.4
Name: LaTeXCalculator
Version: 1.0.1
Summary: A Python package for performing mathematical calculations using LaTeX syntax.
Author: Zhu Chongjing
Author-email: zhuchongjing_pypi@163.com
Classifier: Programming Language :: Python :: 3
Classifier: License :: OSI Approved :: MIT License
Classifier: Operating System :: OS Independent
Requires-Dist: sympy>=1.13.2
Requires-Dist: rich>=14.2.0
Dynamic: author
Dynamic: author-email
Dynamic: classifier
Dynamic: description
Dynamic: description-content-type
Dynamic: requires-dist
Dynamic: summary
